{
  "$schema": "https://tree-sitter.github.io/tree-sitter/assets/schemas/grammar.schema.json",
  "name": "mcc",
  "word": "identifier",
  "rules": {
    "source_file": {
      "type": "SEQ",
      "members": [
        {
          "type": "REPEAT",
          "content": {
            "type": "SYMBOL",
            "name": "import"
          }
        },
        {
          "type": "REPEAT",
          "content": {
            "type": "SYMBOL",
            "name": "_declaration"
          }
        }
      ]
    },
    "import": {
      "type": "SEQ",
      "members": [
        {
          "type": "STRING",
          "value": "import"
        },
        {
          "type": "FIELD",
          "name": "path",
          "content": {
            "type": "SYMBOL",
            "name": "string"
          }
        },
        {
          "type": "STRING",
          "value": ";"
        }
      ]
    },
    "comment": {
      "type": "TOKEN",
      "content": {
        "type": "CHOICE",
        "members": [
          {
            "type": "SEQ",
            "members": [
              {
                "type": "STRING",
                "value": "//"
              },
              {
                "type": "PATTERN",
                "value": "[^\\n]*"
              }
            ]
          },
          {
            "type": "SEQ",
            "members": [
              {
                "type": "STRING",
                "value": "/*"
              },
              {
                "type": "PATTERN",
                "value": "[^*]*\\*+([^/*][^*]*\\*+)*"
              },
              {
                "type": "STRING",
                "value": "/"
              }
            ]
          }
        ]
      }
    },
    "annotation": {
      "type": "CHOICE",
      "members": [
        {
          "type": "PREC_RIGHT",
          "value": 0,
          "content": {
            "type": "SEQ",
            "members": [
              {
                "type": "FIELD",
                "name": "name",
                "content": {
                  "type": "SYMBOL",
                  "name": "annotation_name"
                }
              },
              {
                "type": "CHOICE",
                "members": [
                  {
                    "type": "SEQ",
                    "members": [
                      {
                        "type": "STRING",
                        "value": "("
                      },
                      {
                        "type": "CHOICE",
                        "members": [
                          {
                            "type": "SEQ",
                            "members": [
                              {
                                "type": "CHOICE",
                                "members": [
                                  {
                                    "type": "SYMBOL",
                                    "name": "string"
                                  },
                                  {
                                    "type": "SYMBOL",
                                    "name": "number"
                                  },
                                  {
                                    "type": "SYMBOL",
                                    "name": "identifier"
                                  }
                                ]
                              },
                              {
                                "type": "REPEAT",
                                "content": {
                                  "type": "SEQ",
                                  "members": [
                                    {
                                      "type": "STRING",
                                      "value": ","
                                    },
                                    {
                                      "type": "CHOICE",
                                      "members": [
                                        {
                                          "type": "SYMBOL",
                                          "name": "string"
                                        },
                                        {
                                          "type": "SYMBOL",
                                          "name": "number"
                                        },
                                        {
                                          "type": "SYMBOL",
                                          "name": "identifier"
                                        }
                                      ]
                                    }
                                  ]
                                }
                              }
                            ]
                          },
                          {
                            "type": "BLANK"
                          }
                        ]
                      },
                      {
                        "type": "STRING",
                        "value": ")"
                      }
                    ]
                  },
                  {
                    "type": "BLANK"
                  }
                ]
              }
            ]
          }
        },
        {
          "type": "FIELD",
          "name": "name",
          "content": {
            "type": "ALIAS",
            "content": {
              "type": "STRING",
              "value": "@asm"
            },
            "named": true,
            "value": "annotation_name"
          }
        }
      ]
    },
    "annotation_name": {
      "type": "TOKEN",
      "content": {
        "type": "PATTERN",
        "value": "@[A-Za-z_]\\w*"
      }
    },
    "_declaration": {
      "type": "CHOICE",
      "members": [
        {
          "type": "SYMBOL",
          "name": "struct_declaration"
        },
        {
          "type": "SYMBOL",
          "name": "enum_declaration"
        },
        {
          "type": "SYMBOL",
          "name": "type_alias"
        },
        {
          "type": "SYMBOL",
          "name": "function_definition"
        },
        {
          "type": "SYMBOL",
          "name": "function_prototype"
        },
        {
          "type": "SYMBOL",
          "name": "global_variable"
        },
        {
          "type": "SYMBOL",
          "name": "const_declaration"
        },
        {
          "type": "SYMBOL",
          "name": "conditional"
        },
        {
          "type": "SYMBOL",
          "name": "directive"
        }
      ]
    },
    "directive": {
      "type": "SEQ",
      "members": [
        {
          "type": "FIELD",
          "name": "name",
          "content": {
            "type": "ALIAS",
            "content": {
              "type": "CHOICE",
              "members": [
                {
                  "type": "STRING",
                  "value": "@static_assert"
                },
                {
                  "type": "STRING",
                  "value": "@error"
                },
                {
                  "type": "STRING",
                  "value": "@warning"
                }
              ]
            },
            "named": true,
            "value": "annotation_name"
          }
        },
        {
          "type": "STRING",
          "value": "("
        },
        {
          "type": "SEQ",
          "members": [
            {
              "type": "SYMBOL",
              "name": "_expression"
            },
            {
              "type": "REPEAT",
              "content": {
                "type": "SEQ",
                "members": [
                  {
                    "type": "STRING",
                    "value": ","
                  },
                  {
                    "type": "SYMBOL",
                    "name": "_expression"
                  }
                ]
              }
            }
          ]
        },
        {
          "type": "STRING",
          "value": ")"
        },
        {
          "type": "STRING",
          "value": ";"
        }
      ]
    },
    "struct_declaration": {
      "type": "SEQ",
      "members": [
        {
          "type": "REPEAT",
          "content": {
            "type": "SYMBOL",
            "name": "annotation"
          }
        },
        {
          "type": "CHOICE",
          "members": [
            {
              "type": "STRING",
              "value": "struct"
            },
            {
              "type": "STRING",
              "value": "union"
            }
          ]
        },
        {
          "type": "FIELD",
          "name": "name",
          "content": {
            "type": "ALIAS",
            "content": {
              "type": "SYMBOL",
              "name": "identifier"
            },
            "named": true,
            "value": "type_identifier"
          }
        },
        {
          "type": "CHOICE",
          "members": [
            {
              "type": "SYMBOL",
              "name": "type_parameters"
            },
            {
              "type": "BLANK"
            }
          ]
        },
        {
          "type": "CHOICE",
          "members": [
            {
              "type": "SEQ",
              "members": [
                {
                  "type": "STRING",
                  "value": "extends"
                },
                {
                  "type": "FIELD",
                  "name": "base",
                  "content": {
                    "type": "SYMBOL",
                    "name": "_type"
                  }
                }
              ]
            },
            {
              "type": "BLANK"
            }
          ]
        },
        {
          "type": "CHOICE",
          "members": [
            {
              "type": "STRING",
              "value": ";"
            },
            {
              "type": "SYMBOL",
              "name": "field_list"
            }
          ]
        }
      ]
    },
    "field_list": {
      "type": "SEQ",
      "members": [
        {
          "type": "STRING",
          "value": "{"
        },
        {
          "type": "REPEAT",
          "content": {
            "type": "SEQ",
            "members": [
              {
                "type": "FIELD",
                "name": "name",
                "content": {
                  "type": "SYMBOL",
                  "name": "identifier"
                }
              },
              {
                "type": "STRING",
                "value": ":"
              },
              {
                "type": "SYMBOL",
                "name": "_type"
              },
              {
                "type": "CHOICE",
                "members": [
                  {
                    "type": "SEQ",
                    "members": [
                      {
                        "type": "STRING",
                        "value": "="
                      },
                      {
                        "type": "FIELD",
                        "name": "default",
                        "content": {
                          "type": "SYMBOL",
                          "name": "_expression"
                        }
                      }
                    ]
                  },
                  {
                    "type": "BLANK"
                  }
                ]
              },
              {
                "type": "STRING",
                "value": ";"
              }
            ]
          }
        },
        {
          "type": "STRING",
          "value": "}"
        }
      ]
    },
    "enum_declaration": {
      "type": "SEQ",
      "members": [
        {
          "type": "REPEAT",
          "content": {
            "type": "SYMBOL",
            "name": "annotation"
          }
        },
        {
          "type": "STRING",
          "value": "enum"
        },
        {
          "type": "FIELD",
          "name": "name",
          "content": {
            "type": "ALIAS",
            "content": {
              "type": "SYMBOL",
              "name": "identifier"
            },
            "named": true,
            "value": "type_identifier"
          }
        },
        {
          "type": "CHOICE",
          "members": [
            {
              "type": "SEQ",
              "members": [
                {
                  "type": "STRING",
                  "value": ":"
                },
                {
                  "type": "FIELD",
                  "name": "underlying",
                  "content": {
                    "type": "SYMBOL",
                    "name": "_type"
                  }
                }
              ]
            },
            {
              "type": "BLANK"
            }
          ]
        },
        {
          "type": "SYMBOL",
          "name": "enum_body"
        }
      ]
    },
    "enum_body": {
      "type": "SEQ",
      "members": [
        {
          "type": "STRING",
          "value": "{"
        },
        {
          "type": "CHOICE",
          "members": [
            {
              "type": "SEQ",
              "members": [
                {
                  "type": "SYMBOL",
                  "name": "enum_member"
                },
                {
                  "type": "REPEAT",
                  "content": {
                    "type": "SEQ",
                    "members": [
                      {
                        "type": "STRING",
                        "value": ","
                      },
                      {
                        "type": "SYMBOL",
                        "name": "enum_member"
                      }
                    ]
                  }
                }
              ]
            },
            {
              "type": "BLANK"
            }
          ]
        },
        {
          "type": "CHOICE",
          "members": [
            {
              "type": "STRING",
              "value": ","
            },
            {
              "type": "BLANK"
            }
          ]
        },
        {
          "type": "STRING",
          "value": "}"
        }
      ]
    },
    "enum_member": {
      "type": "SEQ",
      "members": [
        {
          "type": "FIELD",
          "name": "name",
          "content": {
            "type": "SYMBOL",
            "name": "identifier"
          }
        },
        {
          "type": "STRING",
          "value": "="
        },
        {
          "type": "FIELD",
          "name": "value",
          "content": {
            "type": "SYMBOL",
            "name": "_expression"
          }
        }
      ]
    },
    "type_alias": {
      "type": "SEQ",
      "members": [
        {
          "type": "REPEAT",
          "content": {
            "type": "SYMBOL",
            "name": "annotation"
          }
        },
        {
          "type": "STRING",
          "value": "type"
        },
        {
          "type": "FIELD",
          "name": "name",
          "content": {
            "type": "ALIAS",
            "content": {
              "type": "SYMBOL",
              "name": "identifier"
            },
            "named": true,
            "value": "type_identifier"
          }
        },
        {
          "type": "CHOICE",
          "members": [
            {
              "type": "SYMBOL",
              "name": "type_parameters"
            },
            {
              "type": "BLANK"
            }
          ]
        },
        {
          "type": "STRING",
          "value": "="
        },
        {
          "type": "FIELD",
          "name": "value",
          "content": {
            "type": "SYMBOL",
            "name": "_type"
          }
        },
        {
          "type": "STRING",
          "value": ";"
        }
      ]
    },
    "type_parameters": {
      "type": "SEQ",
      "members": [
        {
          "type": "STRING",
          "value": "<"
        },
        {
          "type": "SEQ",
          "members": [
            {
              "type": "SEQ",
              "members": [
                {
                  "type": "ALIAS",
                  "content": {
                    "type": "SYMBOL",
                    "name": "identifier"
                  },
                  "named": true,
                  "value": "type_identifier"
                },
                {
                  "type": "CHOICE",
                  "members": [
                    {
                      "type": "SEQ",
                      "members": [
                        {
                          "type": "STRING",
                          "value": "extends"
                        },
                        {
                          "type": "FIELD",
                          "name": "bound",
                          "content": {
                            "type": "SYMBOL",
                            "name": "_type"
                          }
                        }
                      ]
                    },
                    {
                      "type": "BLANK"
                    }
                  ]
                },
                {
                  "type": "CHOICE",
                  "members": [
                    {
                      "type": "SEQ",
                      "members": [
                        {
                          "type": "STRING",
                          "value": "="
                        },
                        {
                          "type": "FIELD",
                          "name": "default",
                          "content": {
                            "type": "SYMBOL",
                            "name": "_type"
                          }
                        }
                      ]
                    },
                    {
                      "type": "BLANK"
                    }
                  ]
                }
              ]
            },
            {
              "type": "REPEAT",
              "content": {
                "type": "SEQ",
                "members": [
                  {
                    "type": "STRING",
                    "value": ","
                  },
                  {
                    "type": "SEQ",
                    "members": [
                      {
                        "type": "ALIAS",
                        "content": {
                          "type": "SYMBOL",
                          "name": "identifier"
                        },
                        "named": true,
                        "value": "type_identifier"
                      },
                      {
                        "type": "CHOICE",
                        "members": [
                          {
                            "type": "SEQ",
                            "members": [
                              {
                                "type": "STRING",
                                "value": "extends"
                              },
                              {
                                "type": "FIELD",
                                "name": "bound",
                                "content": {
                                  "type": "SYMBOL",
                                  "name": "_type"
                                }
                              }
                            ]
                          },
                          {
                            "type": "BLANK"
                          }
                        ]
                      },
                      {
                        "type": "CHOICE",
                        "members": [
                          {
                            "type": "SEQ",
                            "members": [
                              {
                                "type": "STRING",
                                "value": "="
                              },
                              {
                                "type": "FIELD",
                                "name": "default",
                                "content": {
                                  "type": "SYMBOL",
                                  "name": "_type"
                                }
                              }
                            ]
                          },
                          {
                            "type": "BLANK"
                          }
                        ]
                      }
                    ]
                  }
                ]
              }
            }
          ]
        },
        {
          "type": "STRING",
          "value": ">"
        }
      ]
    },
    "function_definition": {
      "type": "SEQ",
      "members": [
        {
          "type": "REPEAT",
          "content": {
            "type": "SYMBOL",
            "name": "annotation"
          }
        },
        {
          "type": "STRING",
          "value": "fn"
        },
        {
          "type": "FIELD",
          "name": "name",
          "content": {
            "type": "SYMBOL",
            "name": "identifier"
          }
        },
        {
          "type": "CHOICE",
          "members": [
            {
              "type": "SYMBOL",
              "name": "type_parameters"
            },
            {
              "type": "BLANK"
            }
          ]
        },
        {
          "type": "SYMBOL",
          "name": "parameter_list"
        },
        {
          "type": "CHOICE",
          "members": [
            {
              "type": "SEQ",
              "members": [
                {
                  "type": "STRING",
                  "value": "->"
                },
                {
                  "type": "CHOICE",
                  "members": [
                    {
                      "type": "STRING",
                      "value": "mut"
                    },
                    {
                      "type": "BLANK"
                    }
                  ]
                },
                {
                  "type": "FIELD",
                  "name": "return_type",
                  "content": {
                    "type": "SYMBOL",
                    "name": "_type"
                  }
                }
              ]
            },
            {
              "type": "BLANK"
            }
          ]
        },
        {
          "type": "FIELD",
          "name": "body",
          "content": {
            "type": "CHOICE",
            "members": [
              {
                "type": "SYMBOL",
                "name": "block"
              },
              {
                "type": "SYMBOL",
                "name": "asm_block"
              }
            ]
          }
        }
      ]
    },
    "function_prototype": {
      "type": "SEQ",
      "members": [
        {
          "type": "REPEAT",
          "content": {
            "type": "SYMBOL",
            "name": "annotation"
          }
        },
        {
          "type": "STRING",
          "value": "fn"
        },
        {
          "type": "FIELD",
          "name": "name",
          "content": {
            "type": "SYMBOL",
            "name": "identifier"
          }
        },
        {
          "type": "CHOICE",
          "members": [
            {
              "type": "SYMBOL",
              "name": "type_parameters"
            },
            {
              "type": "BLANK"
            }
          ]
        },
        {
          "type": "SYMBOL",
          "name": "parameter_list"
        },
        {
          "type": "CHOICE",
          "members": [
            {
              "type": "SEQ",
              "members": [
                {
                  "type": "STRING",
                  "value": "->"
                },
                {
                  "type": "CHOICE",
                  "members": [
                    {
                      "type": "STRING",
                      "value": "mut"
                    },
                    {
                      "type": "BLANK"
                    }
                  ]
                },
                {
                  "type": "FIELD",
                  "name": "return_type",
                  "content": {
                    "type": "SYMBOL",
                    "name": "_type"
                  }
                }
              ]
            },
            {
              "type": "BLANK"
            }
          ]
        },
        {
          "type": "STRING",
          "value": ";"
        }
      ]
    },
    "parameter_list": {
      "type": "SEQ",
      "members": [
        {
          "type": "STRING",
          "value": "("
        },
        {
          "type": "CHOICE",
          "members": [
            {
              "type": "SEQ",
              "members": [
                {
                  "type": "CHOICE",
                  "members": [
                    {
                      "type": "SYMBOL",
                      "name": "parameter"
                    },
                    {
                      "type": "SYMBOL",
                      "name": "variadic_parameter"
                    }
                  ]
                },
                {
                  "type": "REPEAT",
                  "content": {
                    "type": "SEQ",
                    "members": [
                      {
                        "type": "STRING",
                        "value": ","
                      },
                      {
                        "type": "CHOICE",
                        "members": [
                          {
                            "type": "SYMBOL",
                            "name": "parameter"
                          },
                          {
                            "type": "SYMBOL",
                            "name": "variadic_parameter"
                          }
                        ]
                      }
                    ]
                  }
                }
              ]
            },
            {
              "type": "BLANK"
            }
          ]
        },
        {
          "type": "STRING",
          "value": ")"
        }
      ]
    },
    "parameter": {
      "type": "SEQ",
      "members": [
        {
          "type": "REPEAT",
          "content": {
            "type": "SYMBOL",
            "name": "annotation"
          }
        },
        {
          "type": "CHOICE",
          "members": [
            {
              "type": "CHOICE",
              "members": [
                {
                  "type": "STRING",
                  "value": "const"
                },
                {
                  "type": "STRING",
                  "value": "mut"
                }
              ]
            },
            {
              "type": "BLANK"
            }
          ]
        },
        {
          "type": "FIELD",
          "name": "name",
          "content": {
            "type": "SYMBOL",
            "name": "identifier"
          }
        },
        {
          "type": "STRING",
          "value": ":"
        },
        {
          "type": "SYMBOL",
          "name": "_type"
        }
      ]
    },
    "variadic_parameter": {
      "type": "STRING",
      "value": "..."
    },
    "global_variable": {
      "type": "SEQ",
      "members": [
        {
          "type": "REPEAT",
          "content": {
            "type": "SYMBOL",
            "name": "annotation"
          }
        },
        {
          "type": "STRING",
          "value": "let"
        },
        {
          "type": "FIELD",
          "name": "name",
          "content": {
            "type": "SYMBOL",
            "name": "identifier"
          }
        },
        {
          "type": "CHOICE",
          "members": [
            {
              "type": "SEQ",
              "members": [
                {
                  "type": "STRING",
                  "value": ":"
                },
                {
                  "type": "SYMBOL",
                  "name": "_type"
                }
              ]
            },
            {
              "type": "BLANK"
            }
          ]
        },
        {
          "type": "CHOICE",
          "members": [
            {
              "type": "SEQ",
              "members": [
                {
                  "type": "STRING",
                  "value": "="
                },
                {
                  "type": "FIELD",
                  "name": "value",
                  "content": {
                    "type": "SYMBOL",
                    "name": "_expression"
                  }
                }
              ]
            },
            {
              "type": "BLANK"
            }
          ]
        },
        {
          "type": "STRING",
          "value": ";"
        }
      ]
    },
    "const_declaration": {
      "type": "SEQ",
      "members": [
        {
          "type": "REPEAT",
          "content": {
            "type": "SYMBOL",
            "name": "annotation"
          }
        },
        {
          "type": "STRING",
          "value": "const"
        },
        {
          "type": "FIELD",
          "name": "name",
          "content": {
            "type": "SYMBOL",
            "name": "identifier"
          }
        },
        {
          "type": "CHOICE",
          "members": [
            {
              "type": "SEQ",
              "members": [
                {
                  "type": "STRING",
                  "value": ":"
                },
                {
                  "type": "SYMBOL",
                  "name": "_type"
                }
              ]
            },
            {
              "type": "BLANK"
            }
          ]
        },
        {
          "type": "STRING",
          "value": "="
        },
        {
          "type": "FIELD",
          "name": "value",
          "content": {
            "type": "SYMBOL",
            "name": "_expression"
          }
        },
        {
          "type": "STRING",
          "value": ";"
        }
      ]
    },
    "conditional": {
      "type": "SEQ",
      "members": [
        {
          "type": "FIELD",
          "name": "name",
          "content": {
            "type": "ALIAS",
            "content": {
              "type": "STRING",
              "value": "@if"
            },
            "named": true,
            "value": "annotation_name"
          }
        },
        {
          "type": "STRING",
          "value": "("
        },
        {
          "type": "FIELD",
          "name": "condition",
          "content": {
            "type": "SYMBOL",
            "name": "_expression"
          }
        },
        {
          "type": "STRING",
          "value": ")"
        },
        {
          "type": "FIELD",
          "name": "consequence",
          "content": {
            "type": "SYMBOL",
            "name": "_conditional_body"
          }
        },
        {
          "type": "CHOICE",
          "members": [
            {
              "type": "SEQ",
              "members": [
                {
                  "type": "FIELD",
                  "name": "else",
                  "content": {
                    "type": "ALIAS",
                    "content": {
                      "type": "STRING",
                      "value": "@else"
                    },
                    "named": true,
                    "value": "annotation_name"
                  }
                },
                {
                  "type": "CHOICE",
                  "members": [
                    {
                      "type": "SYMBOL",
                      "name": "conditional"
                    },
                    {
                      "type": "FIELD",
                      "name": "alternative",
                      "content": {
                        "type": "SYMBOL",
                        "name": "_conditional_body"
                      }
                    }
                  ]
                }
              ]
            },
            {
              "type": "BLANK"
            }
          ]
        }
      ]
    },
    "_conditional_body": {
      "type": "CHOICE",
      "members": [
        {
          "type": "SYMBOL",
          "name": "declaration_block"
        },
        {
          "type": "SYMBOL",
          "name": "block"
        }
      ]
    },
    "declaration_block": {
      "type": "SEQ",
      "members": [
        {
          "type": "STRING",
          "value": "{"
        },
        {
          "type": "REPEAT",
          "content": {
            "type": "CHOICE",
            "members": [
              {
                "type": "SYMBOL",
                "name": "_declaration"
              },
              {
                "type": "SYMBOL",
                "name": "import"
              }
            ]
          }
        },
        {
          "type": "STRING",
          "value": "}"
        }
      ]
    },
    "_type": {
      "type": "CHOICE",
      "members": [
        {
          "type": "SYMBOL",
          "name": "const_type"
        },
        {
          "type": "SYMBOL",
          "name": "pointer_type"
        },
        {
          "type": "SYMBOL",
          "name": "array_type"
        },
        {
          "type": "SYMBOL",
          "name": "function_type"
        },
        {
          "type": "SYMBOL",
          "name": "_type_name"
        },
        {
          "type": "SYMBOL",
          "name": "grouped_type"
        }
      ]
    },
    "const_type": {
      "type": "PREC_RIGHT",
      "value": 0,
      "content": {
        "type": "SEQ",
        "members": [
          {
            "type": "STRING",
            "value": "const"
          },
          {
            "type": "SYMBOL",
            "name": "_type"
          }
        ]
      }
    },
    "_type_name": {
      "type": "PREC_RIGHT",
      "value": 0,
      "content": {
        "type": "SEQ",
        "members": [
          {
            "type": "CHOICE",
            "members": [
              {
                "type": "CHOICE",
                "members": [
                  {
                    "type": "STRING",
                    "value": "struct"
                  },
                  {
                    "type": "STRING",
                    "value": "union"
                  }
                ]
              },
              {
                "type": "BLANK"
              }
            ]
          },
          {
            "type": "FIELD",
            "name": "name",
            "content": {
              "type": "ALIAS",
              "content": {
                "type": "SYMBOL",
                "name": "identifier"
              },
              "named": true,
              "value": "type_identifier"
            }
          },
          {
            "type": "CHOICE",
            "members": [
              {
                "type": "SYMBOL",
                "name": "type_arguments"
              },
              {
                "type": "BLANK"
              }
            ]
          }
        ]
      }
    },
    "type_arguments": {
      "type": "SEQ",
      "members": [
        {
          "type": "STRING",
          "value": "<"
        },
        {
          "type": "SEQ",
          "members": [
            {
              "type": "SYMBOL",
              "name": "_type"
            },
            {
              "type": "REPEAT",
              "content": {
                "type": "SEQ",
                "members": [
                  {
                    "type": "STRING",
                    "value": ","
                  },
                  {
                    "type": "SYMBOL",
                    "name": "_type"
                  }
                ]
              }
            }
          ]
        },
        {
          "type": "STRING",
          "value": ">"
        }
      ]
    },
    "pointer_type": {
      "type": "PREC_DYNAMIC",
      "value": -1,
      "content": {
        "type": "PREC",
        "value": 11,
        "content": {
          "type": "SEQ",
          "members": [
            {
              "type": "SYMBOL",
              "name": "_type"
            },
            {
              "type": "REPEAT1",
              "content": {
                "type": "STRING",
                "value": "*"
              }
            }
          ]
        }
      }
    },
    "array_type": {
      "type": "PREC",
      "value": 1,
      "content": {
        "type": "SEQ",
        "members": [
          {
            "type": "SYMBOL",
            "name": "_type"
          },
          {
            "type": "REPEAT1",
            "content": {
              "type": "SYMBOL",
              "name": "dimension"
            }
          }
        ]
      }
    },
    "dimension": {
      "type": "SEQ",
      "members": [
        {
          "type": "STRING",
          "value": "["
        },
        {
          "type": "CHOICE",
          "members": [
            {
              "type": "SYMBOL",
              "name": "_expression"
            },
            {
              "type": "BLANK"
            }
          ]
        },
        {
          "type": "STRING",
          "value": "]"
        }
      ]
    },
    "function_type": {
      "type": "PREC_RIGHT",
      "value": 0,
      "content": {
        "type": "SEQ",
        "members": [
          {
            "type": "STRING",
            "value": "fn"
          },
          {
            "type": "STRING",
            "value": "("
          },
          {
            "type": "CHOICE",
            "members": [
              {
                "type": "SEQ",
                "members": [
                  {
                    "type": "CHOICE",
                    "members": [
                      {
                        "type": "SYMBOL",
                        "name": "_type"
                      },
                      {
                        "type": "SYMBOL",
                        "name": "variadic_parameter"
                      }
                    ]
                  },
                  {
                    "type": "REPEAT",
                    "content": {
                      "type": "SEQ",
                      "members": [
                        {
                          "type": "STRING",
                          "value": ","
                        },
                        {
                          "type": "CHOICE",
                          "members": [
                            {
                              "type": "SYMBOL",
                              "name": "_type"
                            },
                            {
                              "type": "SYMBOL",
                              "name": "variadic_parameter"
                            }
                          ]
                        }
                      ]
                    }
                  }
                ]
              },
              {
                "type": "BLANK"
              }
            ]
          },
          {
            "type": "STRING",
            "value": ")"
          },
          {
            "type": "CHOICE",
            "members": [
              {
                "type": "SEQ",
                "members": [
                  {
                    "type": "STRING",
                    "value": "->"
                  },
                  {
                    "type": "SYMBOL",
                    "name": "_type"
                  }
                ]
              },
              {
                "type": "BLANK"
              }
            ]
          }
        ]
      }
    },
    "grouped_type": {
      "type": "SEQ",
      "members": [
        {
          "type": "STRING",
          "value": "("
        },
        {
          "type": "SYMBOL",
          "name": "_type"
        },
        {
          "type": "STRING",
          "value": ")"
        }
      ]
    },
    "block": {
      "type": "SEQ",
      "members": [
        {
          "type": "STRING",
          "value": "{"
        },
        {
          "type": "REPEAT",
          "content": {
            "type": "SYMBOL",
            "name": "_statement"
          }
        },
        {
          "type": "STRING",
          "value": "}"
        }
      ]
    },
    "_statement": {
      "type": "CHOICE",
      "members": [
        {
          "type": "SYMBOL",
          "name": "block"
        },
        {
          "type": "SYMBOL",
          "name": "return_statement"
        },
        {
          "type": "SYMBOL",
          "name": "emit_statement"
        },
        {
          "type": "SYMBOL",
          "name": "let_statement"
        },
        {
          "type": "SYMBOL",
          "name": "if_statement"
        },
        {
          "type": "SYMBOL",
          "name": "case_statement"
        },
        {
          "type": "SYMBOL",
          "name": "with_statement"
        },
        {
          "type": "SYMBOL",
          "name": "while_statement"
        },
        {
          "type": "SYMBOL",
          "name": "break_statement"
        },
        {
          "type": "SYMBOL",
          "name": "continue_statement"
        },
        {
          "type": "SYMBOL",
          "name": "unreachable_statement"
        },
        {
          "type": "SYMBOL",
          "name": "defer_statement"
        },
        {
          "type": "SYMBOL",
          "name": "for_statement"
        },
        {
          "type": "SYMBOL",
          "name": "conditional"
        },
        {
          "type": "SYMBOL",
          "name": "assignment_statement"
        },
        {
          "type": "SYMBOL",
          "name": "expression_statement"
        }
      ]
    },
    "return_statement": {
      "type": "SEQ",
      "members": [
        {
          "type": "STRING",
          "value": "return"
        },
        {
          "type": "CHOICE",
          "members": [
            {
              "type": "SYMBOL",
              "name": "_expression"
            },
            {
              "type": "BLANK"
            }
          ]
        },
        {
          "type": "STRING",
          "value": ";"
        }
      ]
    },
    "emit_statement": {
      "type": "SEQ",
      "members": [
        {
          "type": "STRING",
          "value": "emit"
        },
        {
          "type": "SYMBOL",
          "name": "_expression"
        },
        {
          "type": "STRING",
          "value": ";"
        }
      ]
    },
    "let_statement": {
      "type": "SEQ",
      "members": [
        {
          "type": "STRING",
          "value": "let"
        },
        {
          "type": "FIELD",
          "name": "name",
          "content": {
            "type": "SYMBOL",
            "name": "identifier"
          }
        },
        {
          "type": "CHOICE",
          "members": [
            {
              "type": "SEQ",
              "members": [
                {
                  "type": "STRING",
                  "value": ":"
                },
                {
                  "type": "SYMBOL",
                  "name": "_type"
                }
              ]
            },
            {
              "type": "BLANK"
            }
          ]
        },
        {
          "type": "CHOICE",
          "members": [
            {
              "type": "SEQ",
              "members": [
                {
                  "type": "STRING",
                  "value": "="
                },
                {
                  "type": "FIELD",
                  "name": "value",
                  "content": {
                    "type": "SYMBOL",
                    "name": "_expression"
                  }
                }
              ]
            },
            {
              "type": "BLANK"
            }
          ]
        },
        {
          "type": "STRING",
          "value": ";"
        }
      ]
    },
    "if_statement": {
      "type": "PREC_RIGHT",
      "value": 0,
      "content": {
        "type": "SEQ",
        "members": [
          {
            "type": "STRING",
            "value": "if"
          },
          {
            "type": "STRING",
            "value": "("
          },
          {
            "type": "FIELD",
            "name": "condition",
            "content": {
              "type": "SYMBOL",
              "name": "_expression"
            }
          },
          {
            "type": "STRING",
            "value": ")"
          },
          {
            "type": "FIELD",
            "name": "consequence",
            "content": {
              "type": "SYMBOL",
              "name": "_body"
            }
          },
          {
            "type": "CHOICE",
            "members": [
              {
                "type": "SEQ",
                "members": [
                  {
                    "type": "STRING",
                    "value": "else"
                  },
                  {
                    "type": "FIELD",
                    "name": "alternative",
                    "content": {
                      "type": "SYMBOL",
                      "name": "_body"
                    }
                  }
                ]
              },
              {
                "type": "BLANK"
              }
            ]
          }
        ]
      }
    },
    "_body": {
      "type": "SYMBOL",
      "name": "_statement"
    },
    "with_statement": {
      "type": "PREC_RIGHT",
      "value": 0,
      "content": {
        "type": "SEQ",
        "members": [
          {
            "type": "STRING",
            "value": "with"
          },
          {
            "type": "STRING",
            "value": "("
          },
          {
            "type": "FIELD",
            "name": "binding",
            "content": {
              "type": "SYMBOL",
              "name": "identifier"
            }
          },
          {
            "type": "STRING",
            "value": "="
          },
          {
            "type": "FIELD",
            "name": "subject",
            "content": {
              "type": "SYMBOL",
              "name": "_expression"
            }
          },
          {
            "type": "STRING",
            "value": ")"
          },
          {
            "type": "FIELD",
            "name": "consequence",
            "content": {
              "type": "SYMBOL",
              "name": "_body"
            }
          },
          {
            "type": "CHOICE",
            "members": [
              {
                "type": "SEQ",
                "members": [
                  {
                    "type": "STRING",
                    "value": "else"
                  },
                  {
                    "type": "FIELD",
                    "name": "alternative",
                    "content": {
                      "type": "SYMBOL",
                      "name": "_body"
                    }
                  }
                ]
              },
              {
                "type": "BLANK"
              }
            ]
          }
        ]
      }
    },
    "case_statement": {
      "type": "SEQ",
      "members": [
        {
          "type": "STRING",
          "value": "case"
        },
        {
          "type": "STRING",
          "value": "("
        },
        {
          "type": "FIELD",
          "name": "subject",
          "content": {
            "type": "SYMBOL",
            "name": "_expression"
          }
        },
        {
          "type": "STRING",
          "value": ")"
        },
        {
          "type": "STRING",
          "value": "{"
        },
        {
          "type": "REPEAT",
          "content": {
            "type": "SYMBOL",
            "name": "when_arm"
          }
        },
        {
          "type": "CHOICE",
          "members": [
            {
              "type": "SYMBOL",
              "name": "else_arm"
            },
            {
              "type": "BLANK"
            }
          ]
        },
        {
          "type": "STRING",
          "value": "}"
        }
      ]
    },
    "when_arm": {
      "type": "SEQ",
      "members": [
        {
          "type": "STRING",
          "value": "when"
        },
        {
          "type": "SEQ",
          "members": [
            {
              "type": "SYMBOL",
              "name": "_expression"
            },
            {
              "type": "REPEAT",
              "content": {
                "type": "SEQ",
                "members": [
                  {
                    "type": "STRING",
                    "value": ","
                  },
                  {
                    "type": "SYMBOL",
                    "name": "_expression"
                  }
                ]
              }
            }
          ]
        },
        {
          "type": "STRING",
          "value": ":"
        },
        {
          "type": "REPEAT",
          "content": {
            "type": "SYMBOL",
            "name": "_statement"
          }
        }
      ]
    },
    "else_arm": {
      "type": "SEQ",
      "members": [
        {
          "type": "STRING",
          "value": "else"
        },
        {
          "type": "STRING",
          "value": ":"
        },
        {
          "type": "REPEAT",
          "content": {
            "type": "SYMBOL",
            "name": "_statement"
          }
        }
      ]
    },
    "while_statement": {
      "type": "SEQ",
      "members": [
        {
          "type": "CHOICE",
          "members": [
            {
              "type": "STRING",
              "value": "while"
            },
            {
              "type": "STRING",
              "value": "until"
            }
          ]
        },
        {
          "type": "STRING",
          "value": "("
        },
        {
          "type": "FIELD",
          "name": "condition",
          "content": {
            "type": "SYMBOL",
            "name": "_expression"
          }
        },
        {
          "type": "STRING",
          "value": ")"
        },
        {
          "type": "FIELD",
          "name": "body",
          "content": {
            "type": "SYMBOL",
            "name": "_body"
          }
        }
      ]
    },
    "break_statement": {
      "type": "SEQ",
      "members": [
        {
          "type": "STRING",
          "value": "break"
        },
        {
          "type": "STRING",
          "value": ";"
        }
      ]
    },
    "continue_statement": {
      "type": "SEQ",
      "members": [
        {
          "type": "STRING",
          "value": "continue"
        },
        {
          "type": "STRING",
          "value": ";"
        }
      ]
    },
    "unreachable_statement": {
      "type": "SEQ",
      "members": [
        {
          "type": "STRING",
          "value": "unreachable"
        },
        {
          "type": "STRING",
          "value": ";"
        }
      ]
    },
    "defer_statement": {
      "type": "SEQ",
      "members": [
        {
          "type": "STRING",
          "value": "defer"
        },
        {
          "type": "SYMBOL",
          "name": "_body"
        }
      ]
    },
    "for_statement": {
      "type": "SEQ",
      "members": [
        {
          "type": "STRING",
          "value": "for"
        },
        {
          "type": "FIELD",
          "name": "variable",
          "content": {
            "type": "SYMBOL",
            "name": "identifier"
          }
        },
        {
          "type": "STRING",
          "value": "in"
        },
        {
          "type": "FIELD",
          "name": "iterable",
          "content": {
            "type": "SYMBOL",
            "name": "_expression"
          }
        },
        {
          "type": "FIELD",
          "name": "body",
          "content": {
            "type": "SYMBOL",
            "name": "_body"
          }
        }
      ]
    },
    "assignment_statement": {
      "type": "SEQ",
      "members": [
        {
          "type": "FIELD",
          "name": "target",
          "content": {
            "type": "SYMBOL",
            "name": "_expression"
          }
        },
        {
          "type": "FIELD",
          "name": "operator",
          "content": {
            "type": "CHOICE",
            "members": [
              {
                "type": "STRING",
                "value": "="
              },
              {
                "type": "STRING",
                "value": "+="
              },
              {
                "type": "STRING",
                "value": "-="
              },
              {
                "type": "STRING",
                "value": "*="
              },
              {
                "type": "STRING",
                "value": "/="
              },
              {
                "type": "STRING",
                "value": "%="
              },
              {
                "type": "STRING",
                "value": "&="
              },
              {
                "type": "STRING",
                "value": "|="
              },
              {
                "type": "STRING",
                "value": "^="
              },
              {
                "type": "STRING",
                "value": "<<="
              },
              {
                "type": "STRING",
                "value": ">>="
              }
            ]
          }
        },
        {
          "type": "FIELD",
          "name": "value",
          "content": {
            "type": "SYMBOL",
            "name": "_expression"
          }
        },
        {
          "type": "STRING",
          "value": ";"
        }
      ]
    },
    "expression_statement": {
      "type": "SEQ",
      "members": [
        {
          "type": "SYMBOL",
          "name": "_expression"
        },
        {
          "type": "STRING",
          "value": ";"
        }
      ]
    },
    "_expression": {
      "type": "CHOICE",
      "members": [
        {
          "type": "SYMBOL",
          "name": "ternary_expression"
        },
        {
          "type": "SYMBOL",
          "name": "logical_expression"
        },
        {
          "type": "SYMBOL",
          "name": "binary_expression"
        },
        {
          "type": "SYMBOL",
          "name": "cast_expression"
        },
        {
          "type": "SYMBOL",
          "name": "unary_expression"
        },
        {
          "type": "SYMBOL",
          "name": "_postfix_expression"
        }
      ]
    },
    "ternary_expression": {
      "type": "PREC_RIGHT",
      "value": 0,
      "content": {
        "type": "SEQ",
        "members": [
          {
            "type": "FIELD",
            "name": "condition",
            "content": {
              "type": "SYMBOL",
              "name": "_expression"
            }
          },
          {
            "type": "STRING",
            "value": "?"
          },
          {
            "type": "FIELD",
            "name": "consequence",
            "content": {
              "type": "SYMBOL",
              "name": "_expression"
            }
          },
          {
            "type": "STRING",
            "value": ":"
          },
          {
            "type": "FIELD",
            "name": "alternative",
            "content": {
              "type": "SYMBOL",
              "name": "_expression"
            }
          }
        ]
      }
    },
    "logical_expression": {
      "type": "CHOICE",
      "members": [
        {
          "type": "PREC_LEFT",
          "value": 1,
          "content": {
            "type": "SEQ",
            "members": [
              {
                "type": "SYMBOL",
                "name": "_expression"
              },
              {
                "type": "STRING",
                "value": "or"
              },
              {
                "type": "SYMBOL",
                "name": "_expression"
              }
            ]
          }
        },
        {
          "type": "PREC_LEFT",
          "value": 2,
          "content": {
            "type": "SEQ",
            "members": [
              {
                "type": "SYMBOL",
                "name": "_expression"
              },
              {
                "type": "STRING",
                "value": "and"
              },
              {
                "type": "SYMBOL",
                "name": "_expression"
              }
            ]
          }
        }
      ]
    },
    "binary_expression": {
      "type": "CHOICE",
      "members": [
        {
          "type": "PREC_LEFT",
          "value": 3,
          "content": {
            "type": "SEQ",
            "members": [
              {
                "type": "SYMBOL",
                "name": "_expression"
              },
              {
                "type": "FIELD",
                "name": "operator",
                "content": {
                  "type": "CHOICE",
                  "members": [
                    {
                      "type": "STRING",
                      "value": "=="
                    },
                    {
                      "type": "STRING",
                      "value": "!="
                    }
                  ]
                }
              },
              {
                "type": "SYMBOL",
                "name": "_expression"
              }
            ]
          }
        },
        {
          "type": "PREC_LEFT",
          "value": 4,
          "content": {
            "type": "SEQ",
            "members": [
              {
                "type": "SYMBOL",
                "name": "_expression"
              },
              {
                "type": "FIELD",
                "name": "operator",
                "content": {
                  "type": "CHOICE",
                  "members": [
                    {
                      "type": "STRING",
                      "value": "<"
                    },
                    {
                      "type": "STRING",
                      "value": "<="
                    },
                    {
                      "type": "STRING",
                      "value": ">"
                    },
                    {
                      "type": "STRING",
                      "value": ">="
                    }
                  ]
                }
              },
              {
                "type": "SYMBOL",
                "name": "_expression"
              }
            ]
          }
        },
        {
          "type": "PREC_LEFT",
          "value": 5,
          "content": {
            "type": "SEQ",
            "members": [
              {
                "type": "SYMBOL",
                "name": "_expression"
              },
              {
                "type": "FIELD",
                "name": "operator",
                "content": {
                  "type": "STRING",
                  "value": "|"
                }
              },
              {
                "type": "SYMBOL",
                "name": "_expression"
              }
            ]
          }
        },
        {
          "type": "PREC_LEFT",
          "value": 6,
          "content": {
            "type": "SEQ",
            "members": [
              {
                "type": "SYMBOL",
                "name": "_expression"
              },
              {
                "type": "FIELD",
                "name": "operator",
                "content": {
                  "type": "STRING",
                  "value": "^"
                }
              },
              {
                "type": "SYMBOL",
                "name": "_expression"
              }
            ]
          }
        },
        {
          "type": "PREC_LEFT",
          "value": 7,
          "content": {
            "type": "SEQ",
            "members": [
              {
                "type": "SYMBOL",
                "name": "_expression"
              },
              {
                "type": "FIELD",
                "name": "operator",
                "content": {
                  "type": "STRING",
                  "value": "&"
                }
              },
              {
                "type": "SYMBOL",
                "name": "_expression"
              }
            ]
          }
        },
        {
          "type": "PREC_LEFT",
          "value": 8,
          "content": {
            "type": "SEQ",
            "members": [
              {
                "type": "SYMBOL",
                "name": "_expression"
              },
              {
                "type": "FIELD",
                "name": "operator",
                "content": {
                  "type": "CHOICE",
                  "members": [
                    {
                      "type": "STRING",
                      "value": "<<"
                    },
                    {
                      "type": "STRING",
                      "value": ">>"
                    }
                  ]
                }
              },
              {
                "type": "SYMBOL",
                "name": "_expression"
              }
            ]
          }
        },
        {
          "type": "PREC_LEFT",
          "value": 9,
          "content": {
            "type": "SEQ",
            "members": [
              {
                "type": "SYMBOL",
                "name": "_expression"
              },
              {
                "type": "FIELD",
                "name": "operator",
                "content": {
                  "type": "CHOICE",
                  "members": [
                    {
                      "type": "STRING",
                      "value": "+"
                    },
                    {
                      "type": "STRING",
                      "value": "-"
                    }
                  ]
                }
              },
              {
                "type": "SYMBOL",
                "name": "_expression"
              }
            ]
          }
        },
        {
          "type": "PREC_LEFT",
          "value": 10,
          "content": {
            "type": "SEQ",
            "members": [
              {
                "type": "SYMBOL",
                "name": "_expression"
              },
              {
                "type": "FIELD",
                "name": "operator",
                "content": {
                  "type": "CHOICE",
                  "members": [
                    {
                      "type": "STRING",
                      "value": "*"
                    },
                    {
                      "type": "STRING",
                      "value": "/"
                    },
                    {
                      "type": "STRING",
                      "value": "%"
                    }
                  ]
                }
              },
              {
                "type": "SYMBOL",
                "name": "_expression"
              }
            ]
          }
        }
      ]
    },
    "cast_expression": {
      "type": "PREC",
      "value": 11,
      "content": {
        "type": "SEQ",
        "members": [
          {
            "type": "SYMBOL",
            "name": "_expression"
          },
          {
            "type": "STRING",
            "value": "as"
          },
          {
            "type": "FIELD",
            "name": "type",
            "content": {
              "type": "SYMBOL",
              "name": "_type"
            }
          }
        ]
      }
    },
    "unary_expression": {
      "type": "PREC_RIGHT",
      "value": 12,
      "content": {
        "type": "SEQ",
        "members": [
          {
            "type": "FIELD",
            "name": "operator",
            "content": {
              "type": "CHOICE",
              "members": [
                {
                  "type": "STRING",
                  "value": "-"
                },
                {
                  "type": "STRING",
                  "value": "!"
                },
                {
                  "type": "STRING",
                  "value": "*"
                },
                {
                  "type": "STRING",
                  "value": "&"
                },
                {
                  "type": "STRING",
                  "value": "~"
                }
              ]
            }
          },
          {
            "type": "SYMBOL",
            "name": "_expression"
          }
        ]
      }
    },
    "_postfix_expression": {
      "type": "CHOICE",
      "members": [
        {
          "type": "SYMBOL",
          "name": "index_expression"
        },
        {
          "type": "SYMBOL",
          "name": "slice_expression"
        },
        {
          "type": "SYMBOL",
          "name": "member_expression"
        },
        {
          "type": "SYMBOL",
          "name": "call_expression"
        },
        {
          "type": "SYMBOL",
          "name": "nonnull_assert_expression"
        },
        {
          "type": "SYMBOL",
          "name": "_primary_expression"
        }
      ]
    },
    "nonnull_assert_expression": {
      "type": "PREC",
      "value": 13,
      "content": {
        "type": "SEQ",
        "members": [
          {
            "type": "FIELD",
            "name": "operand",
            "content": {
              "type": "SYMBOL",
              "name": "_expression"
            }
          },
          {
            "type": "STRING",
            "value": "!"
          }
        ]
      }
    },
    "index_expression": {
      "type": "PREC",
      "value": 13,
      "content": {
        "type": "SEQ",
        "members": [
          {
            "type": "FIELD",
            "name": "base",
            "content": {
              "type": "SYMBOL",
              "name": "_expression"
            }
          },
          {
            "type": "STRING",
            "value": "["
          },
          {
            "type": "FIELD",
            "name": "index",
            "content": {
              "type": "SYMBOL",
              "name": "_expression"
            }
          },
          {
            "type": "STRING",
            "value": "]"
          }
        ]
      }
    },
    "slice_expression": {
      "type": "PREC",
      "value": 13,
      "content": {
        "type": "SEQ",
        "members": [
          {
            "type": "FIELD",
            "name": "base",
            "content": {
              "type": "SYMBOL",
              "name": "_expression"
            }
          },
          {
            "type": "STRING",
            "value": "["
          },
          {
            "type": "CHOICE",
            "members": [
              {
                "type": "FIELD",
                "name": "start",
                "content": {
                  "type": "SYMBOL",
                  "name": "_expression"
                }
              },
              {
                "type": "BLANK"
              }
            ]
          },
          {
            "type": "STRING",
            "value": ":"
          },
          {
            "type": "CHOICE",
            "members": [
              {
                "type": "FIELD",
                "name": "end",
                "content": {
                  "type": "SYMBOL",
                  "name": "_expression"
                }
              },
              {
                "type": "BLANK"
              }
            ]
          },
          {
            "type": "STRING",
            "value": "]"
          }
        ]
      }
    },
    "member_expression": {
      "type": "PREC",
      "value": 13,
      "content": {
        "type": "SEQ",
        "members": [
          {
            "type": "FIELD",
            "name": "base",
            "content": {
              "type": "SYMBOL",
              "name": "_expression"
            }
          },
          {
            "type": "FIELD",
            "name": "operator",
            "content": {
              "type": "CHOICE",
              "members": [
                {
                  "type": "STRING",
                  "value": "."
                },
                {
                  "type": "STRING",
                  "value": "->"
                }
              ]
            }
          },
          {
            "type": "FIELD",
            "name": "field",
            "content": {
              "type": "SYMBOL",
              "name": "identifier"
            }
          }
        ]
      }
    },
    "call_expression": {
      "type": "PREC",
      "value": 14,
      "content": {
        "type": "SEQ",
        "members": [
          {
            "type": "FIELD",
            "name": "function",
            "content": {
              "type": "SYMBOL",
              "name": "_expression"
            }
          },
          {
            "type": "CHOICE",
            "members": [
              {
                "type": "SYMBOL",
                "name": "type_arguments"
              },
              {
                "type": "BLANK"
              }
            ]
          },
          {
            "type": "FIELD",
            "name": "arguments",
            "content": {
              "type": "SYMBOL",
              "name": "argument_list"
            }
          }
        ]
      }
    },
    "argument_list": {
      "type": "SEQ",
      "members": [
        {
          "type": "STRING",
          "value": "("
        },
        {
          "type": "CHOICE",
          "members": [
            {
              "type": "SEQ",
              "members": [
                {
                  "type": "SYMBOL",
                  "name": "_expression"
                },
                {
                  "type": "REPEAT",
                  "content": {
                    "type": "SEQ",
                    "members": [
                      {
                        "type": "STRING",
                        "value": ","
                      },
                      {
                        "type": "SYMBOL",
                        "name": "_expression"
                      }
                    ]
                  }
                }
              ]
            },
            {
              "type": "BLANK"
            }
          ]
        },
        {
          "type": "STRING",
          "value": ")"
        }
      ]
    },
    "_primary_expression": {
      "type": "CHOICE",
      "members": [
        {
          "type": "SYMBOL",
          "name": "number"
        },
        {
          "type": "SYMBOL",
          "name": "float"
        },
        {
          "type": "SYMBOL",
          "name": "string"
        },
        {
          "type": "SYMBOL",
          "name": "char"
        },
        {
          "type": "SYMBOL",
          "name": "boolean"
        },
        {
          "type": "SYMBOL",
          "name": "null"
        },
        {
          "type": "SYMBOL",
          "name": "enum_access"
        },
        {
          "type": "SYMBOL",
          "name": "struct_literal"
        },
        {
          "type": "SYMBOL",
          "name": "identifier_expression"
        },
        {
          "type": "SYMBOL",
          "name": "parenthesized_expression"
        },
        {
          "type": "SYMBOL",
          "name": "block_expression"
        },
        {
          "type": "SYMBOL",
          "name": "array_expression"
        },
        {
          "type": "SYMBOL",
          "name": "sizeof_expression"
        },
        {
          "type": "SYMBOL",
          "name": "alignof_expression"
        },
        {
          "type": "SYMBOL",
          "name": "offsetof_expression"
        },
        {
          "type": "SYMBOL",
          "name": "typename_expression"
        },
        {
          "type": "SYMBOL",
          "name": "len_expression"
        },
        {
          "type": "SYMBOL",
          "name": "asm_expression"
        }
      ]
    },
    "enum_access": {
      "type": "SEQ",
      "members": [
        {
          "type": "FIELD",
          "name": "enum",
          "content": {
            "type": "ALIAS",
            "content": {
              "type": "SYMBOL",
              "name": "identifier"
            },
            "named": true,
            "value": "type_identifier"
          }
        },
        {
          "type": "STRING",
          "value": "::"
        },
        {
          "type": "FIELD",
          "name": "member",
          "content": {
            "type": "SYMBOL",
            "name": "identifier"
          }
        }
      ]
    },
    "struct_literal": {
      "type": "PREC_DYNAMIC",
      "value": 1,
      "content": {
        "type": "SEQ",
        "members": [
          {
            "type": "CHOICE",
            "members": [
              {
                "type": "CHOICE",
                "members": [
                  {
                    "type": "STRING",
                    "value": "struct"
                  },
                  {
                    "type": "STRING",
                    "value": "union"
                  }
                ]
              },
              {
                "type": "BLANK"
              }
            ]
          },
          {
            "type": "FIELD",
            "name": "type",
            "content": {
              "type": "ALIAS",
              "content": {
                "type": "SYMBOL",
                "name": "identifier"
              },
              "named": true,
              "value": "type_identifier"
            }
          },
          {
            "type": "CHOICE",
            "members": [
              {
                "type": "SYMBOL",
                "name": "type_arguments"
              },
              {
                "type": "BLANK"
              }
            ]
          },
          {
            "type": "STRING",
            "value": "{"
          },
          {
            "type": "CHOICE",
            "members": [
              {
                "type": "SEQ",
                "members": [
                  {
                    "type": "SYMBOL",
                    "name": "field_initializer"
                  },
                  {
                    "type": "REPEAT",
                    "content": {
                      "type": "SEQ",
                      "members": [
                        {
                          "type": "STRING",
                          "value": ","
                        },
                        {
                          "type": "SYMBOL",
                          "name": "field_initializer"
                        }
                      ]
                    }
                  }
                ]
              },
              {
                "type": "BLANK"
              }
            ]
          },
          {
            "type": "CHOICE",
            "members": [
              {
                "type": "STRING",
                "value": ","
              },
              {
                "type": "BLANK"
              }
            ]
          },
          {
            "type": "STRING",
            "value": "}"
          }
        ]
      }
    },
    "field_initializer": {
      "type": "SEQ",
      "members": [
        {
          "type": "FIELD",
          "name": "name",
          "content": {
            "type": "SYMBOL",
            "name": "identifier"
          }
        },
        {
          "type": "STRING",
          "value": "="
        },
        {
          "type": "FIELD",
          "name": "value",
          "content": {
            "type": "SYMBOL",
            "name": "_expression"
          }
        }
      ]
    },
    "identifier_expression": {
      "type": "SYMBOL",
      "name": "identifier"
    },
    "parenthesized_expression": {
      "type": "SEQ",
      "members": [
        {
          "type": "STRING",
          "value": "("
        },
        {
          "type": "SYMBOL",
          "name": "_expression"
        },
        {
          "type": "STRING",
          "value": ")"
        }
      ]
    },
    "block_expression": {
      "type": "PREC_DYNAMIC",
      "value": -1,
      "content": {
        "type": "SEQ",
        "members": [
          {
            "type": "STRING",
            "value": "{"
          },
          {
            "type": "REPEAT",
            "content": {
              "type": "SYMBOL",
              "name": "_statement"
            }
          },
          {
            "type": "STRING",
            "value": "}"
          }
        ]
      }
    },
    "array_expression": {
      "type": "SEQ",
      "members": [
        {
          "type": "STRING",
          "value": "["
        },
        {
          "type": "CHOICE",
          "members": [
            {
              "type": "SEQ",
              "members": [
                {
                  "type": "SYMBOL",
                  "name": "_expression"
                },
                {
                  "type": "REPEAT",
                  "content": {
                    "type": "SEQ",
                    "members": [
                      {
                        "type": "STRING",
                        "value": ","
                      },
                      {
                        "type": "SYMBOL",
                        "name": "_expression"
                      }
                    ]
                  }
                }
              ]
            },
            {
              "type": "BLANK"
            }
          ]
        },
        {
          "type": "CHOICE",
          "members": [
            {
              "type": "STRING",
              "value": ","
            },
            {
              "type": "BLANK"
            }
          ]
        },
        {
          "type": "STRING",
          "value": "]"
        }
      ]
    },
    "sizeof_expression": {
      "type": "SEQ",
      "members": [
        {
          "type": "STRING",
          "value": "sizeof"
        },
        {
          "type": "STRING",
          "value": "("
        },
        {
          "type": "SYMBOL",
          "name": "_type"
        },
        {
          "type": "STRING",
          "value": ")"
        }
      ]
    },
    "alignof_expression": {
      "type": "SEQ",
      "members": [
        {
          "type": "STRING",
          "value": "alignof"
        },
        {
          "type": "STRING",
          "value": "("
        },
        {
          "type": "SYMBOL",
          "name": "_type"
        },
        {
          "type": "STRING",
          "value": ")"
        }
      ]
    },
    "offsetof_expression": {
      "type": "SEQ",
      "members": [
        {
          "type": "STRING",
          "value": "offsetof"
        },
        {
          "type": "STRING",
          "value": "("
        },
        {
          "type": "SYMBOL",
          "name": "_type"
        },
        {
          "type": "STRING",
          "value": ","
        },
        {
          "type": "FIELD",
          "name": "field",
          "content": {
            "type": "SYMBOL",
            "name": "identifier"
          }
        },
        {
          "type": "STRING",
          "value": ")"
        }
      ]
    },
    "typename_expression": {
      "type": "SEQ",
      "members": [
        {
          "type": "STRING",
          "value": "typename"
        },
        {
          "type": "STRING",
          "value": "("
        },
        {
          "type": "SYMBOL",
          "name": "_type"
        },
        {
          "type": "STRING",
          "value": ")"
        }
      ]
    },
    "len_expression": {
      "type": "SEQ",
      "members": [
        {
          "type": "STRING",
          "value": "len"
        },
        {
          "type": "STRING",
          "value": "("
        },
        {
          "type": "SYMBOL",
          "name": "_expression"
        },
        {
          "type": "STRING",
          "value": ")"
        }
      ]
    },
    "asm_expression": {
      "type": "SEQ",
      "members": [
        {
          "type": "ALIAS",
          "content": {
            "type": "STRING",
            "value": "@asm"
          },
          "named": true,
          "value": "annotation_name"
        },
        {
          "type": "CHOICE",
          "members": [
            {
              "type": "SYMBOL",
              "name": "clobbers"
            },
            {
              "type": "BLANK"
            }
          ]
        },
        {
          "type": "SYMBOL",
          "name": "argument_list"
        },
        {
          "type": "CHOICE",
          "members": [
            {
              "type": "SEQ",
              "members": [
                {
                  "type": "STRING",
                  "value": "->"
                },
                {
                  "type": "SYMBOL",
                  "name": "_type"
                }
              ]
            },
            {
              "type": "BLANK"
            }
          ]
        },
        {
          "type": "SYMBOL",
          "name": "asm_block"
        }
      ]
    },
    "clobbers": {
      "type": "SEQ",
      "members": [
        {
          "type": "ALIAS",
          "content": {
            "type": "STRING",
            "value": "@clobbers"
          },
          "named": true,
          "value": "annotation_name"
        },
        {
          "type": "STRING",
          "value": "("
        },
        {
          "type": "SEQ",
          "members": [
            {
              "type": "SYMBOL",
              "name": "string"
            },
            {
              "type": "REPEAT",
              "content": {
                "type": "SEQ",
                "members": [
                  {
                    "type": "STRING",
                    "value": ","
                  },
                  {
                    "type": "SYMBOL",
                    "name": "string"
                  }
                ]
              }
            }
          ]
        },
        {
          "type": "STRING",
          "value": ")"
        }
      ]
    },
    "asm_block": {
      "type": "SEQ",
      "members": [
        {
          "type": "STRING",
          "value": "{"
        },
        {
          "type": "REPEAT1",
          "content": {
            "type": "SYMBOL",
            "name": "string"
          }
        },
        {
          "type": "STRING",
          "value": "}"
        }
      ]
    },
    "identifier": {
      "type": "PATTERN",
      "value": "[A-Za-z_]\\w*"
    },
    "number": {
      "type": "TOKEN",
      "content": {
        "type": "CHOICE",
        "members": [
          {
            "type": "PATTERN",
            "value": "0[xX][0-9a-fA-F]+"
          },
          {
            "type": "PATTERN",
            "value": "\\d+"
          }
        ]
      }
    },
    "float": {
      "type": "TOKEN",
      "content": {
        "type": "CHOICE",
        "members": [
          {
            "type": "PATTERN",
            "value": "\\d+\\.\\d+([eE][+-]?\\d+)?"
          },
          {
            "type": "PATTERN",
            "value": "\\d+[eE][+-]?\\d+"
          }
        ]
      }
    },
    "string": {
      "type": "TOKEN",
      "content": {
        "type": "SEQ",
        "members": [
          {
            "type": "STRING",
            "value": "\""
          },
          {
            "type": "REPEAT",
            "content": {
              "type": "CHOICE",
              "members": [
                {
                  "type": "PATTERN",
                  "value": "[^\"\\\\\\n]"
                },
                {
                  "type": "PATTERN",
                  "value": "\\\\."
                }
              ]
            }
          },
          {
            "type": "STRING",
            "value": "\""
          }
        ]
      }
    },
    "char": {
      "type": "TOKEN",
      "content": {
        "type": "SEQ",
        "members": [
          {
            "type": "STRING",
            "value": "'"
          },
          {
            "type": "CHOICE",
            "members": [
              {
                "type": "PATTERN",
                "value": "[^'\\\\\\n]"
              },
              {
                "type": "PATTERN",
                "value": "\\\\."
              }
            ]
          },
          {
            "type": "STRING",
            "value": "'"
          }
        ]
      }
    },
    "boolean": {
      "type": "CHOICE",
      "members": [
        {
          "type": "STRING",
          "value": "true"
        },
        {
          "type": "STRING",
          "value": "false"
        }
      ]
    },
    "null": {
      "type": "STRING",
      "value": "null"
    }
  },
  "extras": [
    {
      "type": "PATTERN",
      "value": "\\s"
    },
    {
      "type": "SYMBOL",
      "name": "comment"
    }
  ],
  "conflicts": [
    [
      "identifier_expression",
      "_type_name"
    ],
    [
      "binary_expression",
      "call_expression"
    ],
    [
      "binary_expression",
      "unary_expression",
      "call_expression"
    ],
    [
      "block",
      "block_expression"
    ],
    [
      "declaration_block",
      "block"
    ],
    [
      "_declaration",
      "_statement"
    ],
    [
      "global_variable",
      "let_statement"
    ],
    [
      "argument_list",
      "parenthesized_expression"
    ],
    [
      "struct_literal",
      "identifier_expression"
    ],
    [
      "struct_literal",
      "identifier_expression",
      "_type_name"
    ],
    [
      "pointer_type",
      "cast_expression"
    ]
  ],
  "precedences": [],
  "externals": [],
  "inline": [],
  "supertypes": [],
  "reserved": {}
}